{
  "name": "integra-control-tower-backend",
  "version": "1.0.0",
  "description": "Backend MVP para Integra Control Tower - Sistema de financiamiento de importaciones",
  "main": "dist/app.js",
  "scripts": {
    "build": "tsc",
    "start": "node dist/app.js",
    "dev": "ts-node-dev --respawn --transpile-only src/app.ts",
    "test": "jest",
    "test:watch": "jest --watch",
    "lint": "eslint src/**/*.ts",
    "lint:fix": "eslint src/**/*.ts --fix",
    "typecheck": "tsc --noEmit"
  },
  "keywords": [
    "import-financing",
    "trade-finance",
    "mvp",
    "typescript",
    "express"
  ],
  "author": "Integra Team",
  "license": "ISC",
  "dependencies": {
    "express": "^4.18.2",
    "cors": "^2.8.5",
    "helmet": "^7.1.0",
    "compression": "^1.7.4",
    "morgan": "^1.10.0",
    "jsonwebtoken": "^9.0.2",
    "bcryptjs": "^2.4.3",
    "joi": "^17.11.0",
    "pg": "^8.11.3",
    "typeorm": "^0.3.17",
    "reflect-metadata": "^0.1.13",
    "class-validator": "^0.14.0",
    "class-transformer": "^0.5.1",
    "multer": "^1.4.5-lts.1",
    "uuid": "^9.0.1",
    "moment": "^2.29.4",
    "winston": "^3.11.0",
    "dotenv": "^16.3.1"
  },
  "devDependencies": {
    "@types/express": "^4.17.21",
    "@types/cors": "^2.8.17",
    "@types/compression": "^1.7.5",
    "@types/morgan": "^1.9.9",
    "@types/jsonwebtoken": "^9.0.5",
    "@types/bcryptjs": "^2.4.6",
    "@types/joi": "^17.2.3",
    "@types/pg": "^8.10.9",
    "@types/multer": "^1.4.11",
    "@types/uuid": "^9.0.7",
    "@types/node": "^20.10.4",
    "@types/jest": "^29.5.8",
    "typescript": "^5.3.3",
    "ts-node": "^10.9.1",
    "ts-node-dev": "^2.0.0",
    "jest": "^29.7.0",
    "ts-jest": "^29.1.1",
    "@typescript-eslint/eslint-plugin": "^6.13.1",
    "@typescript-eslint/parser": "^6.13.1",
    "eslint": "^8.54.0",
    "eslint-config-prettier": "^9.0.0",
    "eslint-plugin-prettier": "^5.0.1",
    "prettier": "^3.1.0"
  },
  "engines": {
    "node": ">=18.0.0",
    "npm": ">=8.0.0"
  },
  "repository": {
    "type": "git",
    "url": "git+https://github.com/integra/control-tower-backend.git"
  },
  "bugs": {
    "url": "https://github.com/integra/control-tower-backend/issues"
  },
  "homepage": "https://github.com/integra/control-tower-backend#readme"
}